toloka_airflow/__init__.py
toloka_airflow/hook_decorators.py
toloka_airflow/hooks.py
toloka_airflow/operators.py
toloka_airflow/util.py
toloka_airflow-0.0.3.dist-info/AUTHORS
toloka_airflow-0.0.3.dist-info/LICENSE
toloka_airflow-0.0.3.dist-info/METADATA
toloka_airflow-0.0.3.dist-info/WHEEL
toloka_airflow-0.0.3.dist-info/top_level.txt
toloka_airflow-0.0.3.dist-info/RECORD
